LICENSE
MANIFEST.in
Makefile
README.md
requirements.txt
requirements_dev.txt
setup.py
askme/__init__.py
askme/aws.py
askme/constants.py
askme/digitalocean.py
askme/gcloud.py
askme/main.py
askme/provider.py
askme.egg-info/PKG-INFO
askme.egg-info/SOURCES.txt
askme.egg-info/dependency_links.txt
askme.egg-info/entry_points.txt
askme.egg-info/top_level.txt
askme/source/data/aws.json
askme/source/data/digitalocean.json
askme/source/data/gcloud.json