Metadata-Version: 1.1
Name: askme
Version: 0.0.4
Summary: AskMe Python Client
Home-page: https://github.com/pirsquare/askme-python
Author: Ryan Liao
Author-email: pirsquare.ryan@gmail.com
License: MIT
Platform: UNKNOWN
Classifier: Development Status :: 4 - Beta
Classifier: Environment :: Web Environment
Classifier: Intended Audience :: Developers
Classifier: Operating System :: OS Independent
Classifier: Programming Language :: Python
